fds/__init__.py
fds/sdk/__init__.py
fds/sdk/VirtualPortfolioAPIforDigitalPortals/__init__.py
fds/sdk/VirtualPortfolioAPIforDigitalPortals/api_client.py
fds/sdk/VirtualPortfolioAPIforDigitalPortals/configuration.py
fds/sdk/VirtualPortfolioAPIforDigitalPortals/exceptions.py
fds/sdk/VirtualPortfolioAPIforDigitalPortals/model_utils.py
fds/sdk/VirtualPortfolioAPIforDigitalPortals/rest.py
fds/sdk/VirtualPortfolioAPIforDigitalPortals/api/__init__.py
fds/sdk/VirtualPortfolioAPIforDigitalPortals/api/portfolio_api.py
fds/sdk/VirtualPortfolioAPIforDigitalPortals/api/watchlist_api.py
fds/sdk/VirtualPortfolioAPIforDigitalPortals/apis/__init__.py
fds/sdk/VirtualPortfolioAPIforDigitalPortals/model/__init__.py
fds/sdk/VirtualPortfolioAPIforDigitalPortals/model/attributes_member.py
fds/sdk/VirtualPortfolioAPIforDigitalPortals/model/cursor_based_pagination_output_object.py
fds/sdk/VirtualPortfolioAPIforDigitalPortals/model/cursor_based_pagination_output_object_without_total.py
fds/sdk/VirtualPortfolioAPIforDigitalPortals/model/error_meta_object.py
fds/sdk/VirtualPortfolioAPIforDigitalPortals/model/error_object.py
fds/sdk/VirtualPortfolioAPIforDigitalPortals/model/inline_object.py
fds/sdk/VirtualPortfolioAPIforDigitalPortals/model/inline_object1.py
fds/sdk/VirtualPortfolioAPIforDigitalPortals/model/inline_object10.py
fds/sdk/VirtualPortfolioAPIforDigitalPortals/model/inline_object11.py
fds/sdk/VirtualPortfolioAPIforDigitalPortals/model/inline_object12.py
fds/sdk/VirtualPortfolioAPIforDigitalPortals/model/inline_object13.py
fds/sdk/VirtualPortfolioAPIforDigitalPortals/model/inline_object14.py
fds/sdk/VirtualPortfolioAPIforDigitalPortals/model/inline_object15.py
fds/sdk/VirtualPortfolioAPIforDigitalPortals/model/inline_object16.py
fds/sdk/VirtualPortfolioAPIforDigitalPortals/model/inline_object17.py
fds/sdk/VirtualPortfolioAPIforDigitalPortals/model/inline_object18.py
fds/sdk/VirtualPortfolioAPIforDigitalPortals/model/inline_object19.py
fds.sdk.VirtualPortfolioAPIforDigitalPortals-0.9.5.dist-info/LICENSE
fds.sdk.VirtualPortfolioAPIforDigitalPortals-0.9.5.dist-info/METADATA
fds.sdk.VirtualPortfolioAPIforDigitalPortals-0.9.5.dist-info/WHEEL
fds.sdk.VirtualPortfolioAPIforDigitalPortals-0.9.5.dist-info/top_level.txt
fds.sdk.VirtualPortfolioAPIforDigitalPortals-0.9.5.dist-info/RECORD
